aiida_bader/__init__.py
aiida_bader/__main__.py
aiida_bader/utils.py
aiida_bader/calculations/__init__.py
aiida_bader/parsers/__init__.py
aiida_bader/qeapp/__init__.py
aiida_bader/qeapp/model.py
aiida_bader/qeapp/resources.py
aiida_bader/qeapp/setting.py
aiida_bader/qeapp/workchain.py
aiida_bader/qeapp/guides/0_Basic tutorial.html
aiida_bader/qeapp/result/__init__.py
aiida_bader/qeapp/result/model.py
aiida_bader/qeapp/result/panel.py
aiida_bader/qeapp/structure_examples/PtO.cif
aiida_bader/qeapp/structure_examples/PtO2.cif
aiida_bader/qeapp/structure_examples/__init__.py
aiida_bader/workchains/__init__.py
aiida_bader/workchains/qe_bader.py
aiida_bader/workchains/protocols/__init__.py
aiida_bader/workchains/protocols/bader.yaml
aiida_bader/workgraph/__init__.py
aiida_bader/workgraph/cp2k_bader.py
aiida_bader/workgraph/qe_bader.py
aiida_bader-0.1.8.dist-info/entry_points.txt
aiida_bader-0.1.8.dist-info/licenses/LICENSE
aiida_bader-0.1.8.dist-info/WHEEL
aiida_bader-0.1.8.dist-info/METADATA
aiida_bader-0.1.8.dist-info/RECORD
